birdhousebuilder.recipe.redis-0.1.0-py2.7-nspkg.pth
birdhousebuilder/recipe/redis/__init__.py
birdhousebuilder/recipe/redis/recipe.rst
birdhousebuilder/recipe/redis/redis.conf
birdhousebuilder/recipe/redis/tests/__init__.py
birdhousebuilder/recipe/redis/tests/test_docs.py
birdhousebuilder.recipe.redis-0.1.0.dist-info/DESCRIPTION.rst
birdhousebuilder.recipe.redis-0.1.0.dist-info/METADATA
birdhousebuilder.recipe.redis-0.1.0.dist-info/RECORD
birdhousebuilder.recipe.redis-0.1.0.dist-info/WHEEL
birdhousebuilder.recipe.redis-0.1.0.dist-info/entry_points.txt
birdhousebuilder.recipe.redis-0.1.0.dist-info/metadata.json
birdhousebuilder.recipe.redis-0.1.0.dist-info/namespace_packages.txt
birdhousebuilder.recipe.redis-0.1.0.dist-info/pbr.json
birdhousebuilder.recipe.redis-0.1.0.dist-info/top_level.txt
