Metadata-Version: 2.0
Name: birdhousebuilder.recipe.redis
Version: 0.1.0
Summary: A Buildout recipe to install and configure Redis for Birdhouse.
Home-page: https://github.com/bird-house/birdhousebuilder.recipe.redis
Author: Birdhouse
Author-email: UNKNOWN
License: Apache License 2.0
Keywords: buildout recipe birdhouse conda celery redis
Platform: UNKNOWN
Classifier: Framework :: Buildout
Classifier: Intended Audience :: Developers
Classifier: Topic :: Software Development :: Build Tools
Classifier: Topic :: Software Development :: Libraries :: Python Modules
Classifier: License :: OSI Approved :: Apache Software License
Requires-Dist: Mako
Requires-Dist: birdhousebuilder.recipe.conda
Requires-Dist: birdhousebuilder.recipe.supervisor
Requires-Dist: setuptools
Requires-Dist: zc.buildout
Provides-Extra: tests
Requires-Dist: manuel; extra == 'tests'
Requires-Dist: zc.buildout; extra == 'tests'
Requires-Dist: zope.testing; extra == 'tests'
